nemed/__init__.py
nemed/data/__init__.py
nemed/data/duid_mapping.csv
nemed/data/existing_gen_data_summary.csv
nemed/data/plant_auxiliary/_plant_auxload_assumptions.csv
nemed/data/plant_auxiliary/comparison.xlsx
nemed/data/plant_auxiliary/readme.txt
nemed/defaults.py
nemed/downloader.py
nemed/helper_functions/__init__.py
nemed/helper_functions/helpers.py
nemed/helper_functions/mod_nemosis.py
nemed/helper_functions/mod_xml_cache.py
nemed/nemed.py
nemed/process.py
nemed-0.3.3.dist-info/LICENSE
nemed-0.3.3.dist-info/WHEEL
nemed-0.3.3.dist-info/METADATA
nemed-0.3.3.dist-info/RECORD
