Metadata-Version: 2.1
Name: nemed
Version: 0.3.3
Summary: NEM Emissions Data tool
License: Licence
Author: Declan Heim
Requires-Python: >=3.8,<4.0
Classifier: License :: Other/Proprietary License
Classifier: Programming Language :: Python :: 3
Classifier: Programming Language :: Python :: 3.8
Classifier: Programming Language :: Python :: 3.9
Classifier: Programming Language :: Python :: 3.10
Classifier: Programming Language :: Python :: 3.11
Requires-Dist: datetime
Requires-Dist: joblib (>=1.2.0,<2.0.0)
Requires-Dist: nemosis
Requires-Dist: nempy
Requires-Dist: pandas (>=1.2,<2.0)
Requires-Dist: pathlib
Requires-Dist: plotly
Requires-Dist: requests
Requires-Dist: tqdm
Requires-Dist: xmltodict
